georgescalc/__init__.py
georgescalc/equations.py
georgescalc/functions.py
georgescalc/total.py
georgescalc-0.0.1.dist-info/METADATA
georgescalc-0.0.1.dist-info/WHEEL
georgescalc-0.0.1.dist-info/top_level.txt
georgescalc-0.0.1.dist-info/RECORD
