Metadata-Version: 2.1
Name: georgescalc
Version: 0.0.1
Summary: Mix of functions
Home-page: https://github.com/georgecnha/georges_calc
Author: George Pontes da Cunha
Author-email: george.pontes02@gmail.com
License: UNKNOWN
Platform: UNKNOWN
Requires-Python: >=3.8
